goldlink/__init__.py
goldlink/constants.py
goldlink/errors.py
goldlink/goldlink_client.py
goldlink/helpers.py
goldlink/abi/erc20.json
goldlink/abi/gmx-frf-account-getters.json
goldlink/abi/gmx-frf-strategy-account.json
goldlink/abi/gmx-frf-strategy-manager.json
goldlink/abi/gmx-v2-reader.json
goldlink/abi/gmx_v2_reader.json
goldlink/abi/igmx-v2-datastore.json
goldlink/abi/strategy-account.json
goldlink/abi/strategy-bank.json
goldlink/abi/strategy-reserve.json
integration_tests/__init__.py
integration_tests/constants.py
integration_tests/test_client.py
goldlink_client_python-0.0.9.dist-info/LICENSE
goldlink_client_python-0.0.9.dist-info/METADATA
goldlink_client_python-0.0.9.dist-info/WHEEL
goldlink_client_python-0.0.9.dist-info/top_level.txt
goldlink_client_python-0.0.9.dist-info/RECORD
